gcode_documentation_parser/__init__.py
gcode_documentation_parser/parser/__init__.py
gcode_documentation_parser/parser/base_parser.py
gcode_documentation_parser/parser/parser_registry.py
gcode_documentation_parser/parser/parsers/__init__.py
gcode_documentation_parser/parser/parsers/klipper.py
gcode_documentation_parser/parser/parsers/marlin.py
gcode_documentation_parser/parser/parsers/reprap.py
gcode_documentation_parser/updater.py
gcode_documentation_parser-0.1.0.dist-info/LICENSE
gcode_documentation_parser-0.1.0.dist-info/WHEEL
gcode_documentation_parser-0.1.0.dist-info/METADATA
gcode_documentation_parser-0.1.0.dist-info/RECORD
