Metadata-Version: 2.1
Name: gcode-documentation-parser
Version: 0.1.0
Summary: A utility that parses the documentation pages from Marlin, RepRap, and Klipper, to generate an index of commands usage
Home-page: https://costas-basdekis.github.io/gcode-documentation-parser
License: MIT
Keywords: gcode,marlin,reprap,klipper
Author: Costas Basdekis
Author-email: code@basdekis.io
Requires-Python: >=3.8,<4.0
Classifier: Development Status :: 1 - Planning
Classifier: Environment :: Console
Classifier: Intended Audience :: Developers
Classifier: License :: OSI Approved :: MIT License
Classifier: Natural Language :: English
Classifier: Programming Language :: Python :: 3
Classifier: Programming Language :: Python :: 3.10
Classifier: Programming Language :: Python :: 3.8
Classifier: Programming Language :: Python :: 3.9
Classifier: Topic :: Documentation
Requires-Dist: beautifulsoup4 (>=4,<4.10.0)
Requires-Dist: wikitextparser (>=0.45.2,<0.46.0)
Project-URL: Documentation, https://costas-basdekis.github.io/gcode-documentation-parser
Project-URL: Repository, https://costas-basdekis.github.io/gcode-documentation-parser
